MiraTitanHMFemulator/GP_matrix.py
MiraTitanHMFemulator/MiraTitanHMFemulator.py
MiraTitanHMFemulator/VERSION
MiraTitanHMFemulator/__init__.py
MiraTitanHMFemulator/data/GP_params_mean.npy
MiraTitanHMFemulator/data/GP_params_std.npy
MiraTitanHMFemulator/data/PCA_mean_std_transform_0.npy
MiraTitanHMFemulator/data/PCA_mean_std_transform_1.npy
MiraTitanHMFemulator/data/PCA_mean_std_transform_2.npy
MiraTitanHMFemulator/data/PCA_mean_std_transform_3.npy
MiraTitanHMFemulator/data/PCA_mean_std_transform_4.npy
MiraTitanHMFemulator/data/PCA_mean_std_transform_5.npy
MiraTitanHMFemulator/data/PCA_mean_std_transform_6.npy
MiraTitanHMFemulator/data/PCA_mean_std_transform_7.npy
MiraTitanHMFemulator/data/cov_n.npy
MiraTitanHMFemulator/data/facs.npy
MiraTitanHMFemulator/data/hyperparams.npy
MiraTitanHMFemulator/data/means.npy
MiraTitanHMFemulator/data/params_design_w0wb.npy
MiraTitanHMFemulator/tests/fid.npy
MiraTitanHMFemulator/tests/fid_err.npy
MiraTitanHMFemulator/tests/mid.npy
MiraTitanHMFemulator/tests/mid_err.npy
MiraTitanHMFemulator/tests/test_MiraTitanHMFemulator.py
MiraTitanHMFemulator-0.1.1.dist-info/LICENSE
MiraTitanHMFemulator-0.1.1.dist-info/METADATA
MiraTitanHMFemulator-0.1.1.dist-info/WHEEL
MiraTitanHMFemulator-0.1.1.dist-info/top_level.txt
MiraTitanHMFemulator-0.1.1.dist-info/RECORD
