Metadata-Version: 2.1
Name: MiraTitanHMFemulator
Version: 0.1.1
Summary: Mira-Titan Universe: Halo mass function emulator
Home-page: https://github.com/SebastianBocquet/MiraTitanHMFemulator
Author: Sebastian Bocquet
Author-email: sebastian.bocquet@gmail.com
License: UNKNOWN
Platform: UNKNOWN
Classifier: Programming Language :: Python :: 2
Classifier: Programming Language :: Python :: 3
Classifier: License :: OSI Approved :: MIT License
Classifier: Operating System :: OS Independent
Requires-Dist: numpy
Requires-Dist: scipy
